manage.py
settings.py
b2_forms/__init__.py
b2_forms/admin.py
b2_forms/apps.py
b2_forms/enums.py
b2_forms/helpers.py
b2_forms/mixins.py
b2_forms/models.py
b2_forms/signals.py
b2_forms/migrations/0001_initial.py
b2_forms/migrations/__init__.py
b2_forms/tests/__init__.py
b2_forms/tests/helpers.py
b2_forms-0.0.2.dist-info/METADATA
b2_forms-0.0.2.dist-info/WHEEL
b2_forms-0.0.2.dist-info/top_level.txt
b2_forms-0.0.2.dist-info/RECORD
