Metadata-Version: 2.1
Name: b2-forms
Version: 0.0.2
Summary: A useful package provided by B2BIT
Author-email: Felipe Sena 🏎️ <felipesena@b2bit.company>
Project-URL: Homepage, https://gitlab.com/b2bit.felipesena/b2-forms
Classifier: Programming Language :: Python :: 3
Classifier: License :: OSI Approved :: MIT License
Classifier: Operating System :: OS Independent
Requires-Python: >=3.7
Requires-Dist: Django >=4.0.6
Requires-Dist: django-model-utils >=4.3.1
Requires-Dist: djangorestframework >=3.13.1
Requires-Dist: model-bakery >=1.9.0
Requires-Dist: Faker >=13.3.4
Requires-Dist: Pillow >=9.4.0
Requires-Dist: validate-docbr >=1.10.0
Requires-Dist: celery >=5.2.7
